{"cameraMode":{"drawMode":0,"name":"Shaded","section":"Shading Mode"},"sceneLighting":false,"audioPlay":false,"sceneViewState":{"showFog":true,"showMaterialUpdate":false,"showSkybox":false,"showFlares":true,"showImageEffects":true,"showParticleSystems":true},"in2DMode":false,"pivot":{"x":0.24292713403701783,"y":-0.7133634090423584,"z":0.03985574096441269},"rotation":{"x":-0.0073922863230109219,"y":-0.3225220739841461,"z":0.002520521404221654,"w":-0.9465298056602478},"size":0.5411347150802612,"orthographic":false}